{"cameraMode":{"drawMode":0,"name":"Shaded","section":"Shading Mode"},"sceneLighting":true,"audioPlay":false,"sceneViewState":{"showFog":true,"showMaterialUpdate":false,"showSkybox":true,"showFlares":true,"showImageEffects":true,"showParticleSystems":true},"in2DMode":false,"pivot":{"x":-4.417181015014648,"y":-0.6046009063720703,"z":-14.663437843322754},"rotation":{"x":-0.11416693031787873,"y":0.8064814805984497,"z":-0.16557621955871583,"w":-0.5560207962989807},"size":16.650390625,"orthographic":false}